mkdocs_apidescribed/__init__.py
mkdocs_apidescribed/config.py
mkdocs_apidescribed/extension.py
mkdocs_apidescribed/formatter.py
mkdocs_apidescribed/inspector.py
mkdocs_apidescribed/parsers.py
mkdocs_apidescribed/plugin.py
mkdocs_apidescribed/probe.py
mkdocs_apidescribed_plugin-1.2.0.dist-info/METADATA
mkdocs_apidescribed_plugin-1.2.0.dist-info/WHEEL
mkdocs_apidescribed_plugin-1.2.0.dist-info/entry_points.txt
mkdocs_apidescribed_plugin-1.2.0.dist-info/licenses/LICENSE
mkdocs_apidescribed_plugin-1.2.0.dist-info/RECORD
