Metadata-Version: 2.4
Name: mkdocs-apidescribed-plugin
Version: 1.2.0
Summary: mkdocs plugin to generate API documentation for Python programs
Project-URL: Homepage, https://github.com/idlesign/mkdocs-apidescribed-plugin
Project-URL: Documentation, https://mkdocs-apidescribed-plugin.readthedocs.org/
Author-email: Igor Starikov <idlesign@yandex.ru>
License-Expression: BSD-3-Clause
License-File: LICENSE
Keywords: api,mkdocs,plugin
Requires-Python: >=3.10
Requires-Dist: griffe
Requires-Dist: mkdocs
Requires-Dist: pyyaml
